README.rst
setup.py
avpclient/__init__.py
avpclient/constants.py
avpclient.egg-info/PKG-INFO
avpclient.egg-info/SOURCES.txt
avpclient.egg-info/dependency_links.txt
avpclient.egg-info/not-zip-safe
avpclient.egg-info/requires.txt
avpclient.egg-info/top_level.txt
avpclient/performance_analysis/__init__.py
avpclient/performance_analysis/api.py
avpclient/performance_analysis/async_api.py
avpclient/performance_analysis/engine.py